eggcellent/__init__.py
eggcellent/eggcellent.py
eggcellent-0.1.1.dist-info/METADATA
eggcellent-0.1.1.dist-info/RECORD
eggcellent-0.1.1.dist-info/WHEEL
eggcellent-0.1.1.dist-info/top_level.txt
eggcellent-0.1.1.dist-info/zip-safe
