Metadata-Version: 2.1
Name: eggcellent
Version: 0.1.1
Summary: Egg shapes.
Home-page: https://github.com/davipatti/eggcellent
Author: David Pattinson
Author-email: davipatti10@gmail.com
Maintainer: David Pattinson
Maintainer-email: davipatti10@gmail.com
License: MIT
Download-URL: https://github.com/davipatti/eggcellent/releases/latest
Keywords: egg
Platform: Linux
Platform: MacOS
Platform: Windows
Classifier: Development Status :: 4 - Beta
Classifier: Environment :: Console
Classifier: Programming Language :: Python
